jaminit/__init__.py
jaminit/cli.py
jaminit/generator.py
jaminit/utils.py
jaminit-0.1.0.dist-info/licenses/LICENSE
jaminit-0.1.0.dist-info/METADATA
jaminit-0.1.0.dist-info/WHEEL
jaminit-0.1.0.dist-info/entry_points.txt
jaminit-0.1.0.dist-info/top_level.txt
jaminit-0.1.0.dist-info/RECORD
