Metadata-Version: 2.4
Name: jaminit
Version: 0.1.0
Summary: A command-line tool for initializing structured game jam projects.
Home-page: https://github.com/egeltorp/jaminit
Author: Theodor Holmberg
Author-email: Theodor Holmberg <35803316+egeltorp@users.noreply.github.com>
Maintainer: Theodor Holmberg
License: MIT
Project-URL: Homepage, https://github.com/egeltorp/jaminit
Project-URL: Issues, https://github.com/egeltorp/jaminit/issues
Keywords: gamedev,tooling,cli,automation,game jam
Classifier: Programming Language :: Python :: 3
Classifier: Programming Language :: Python :: 3.10
Classifier: License :: OSI Approved :: MIT License
Classifier: Operating System :: OS Independent
Classifier: Intended Audience :: Developers
Classifier: Topic :: Software Development :: Build Tools
Classifier: Topic :: Games/Entertainment
Requires-Python: >=3.10
License-File: LICENSE
Requires-Dist: argparse
Requires-Dist: jinja2
Requires-Dist: rich
Requires-Dist: pyyaml
Requires-Dist: requests
Provides-Extra: dev
Requires-Dist: pytest; extra == "dev"
Requires-Dist: black; extra == "dev"
Dynamic: license-file
